firelight/__init__.py
firelight/firelight.py
firelight/interfaces/__init__.py
firelight/interfaces/color.py
firelight/interfaces/light.py
firelight/interfaces/lifx/__init__.py
firelight/interfaces/lifx/lifx.py
firelight/processing/__init__.py
firelight/processing/image.py
firelight/processing/quantizer.py
firelight/processing/screen_processor.py
firelight_lighting-1.0.1.dist-info/LICENSE
firelight_lighting-1.0.1.dist-info/METADATA
firelight_lighting-1.0.1.dist-info/WHEEL
firelight_lighting-1.0.1.dist-info/entry_points.txt
firelight_lighting-1.0.1.dist-info/top_level.txt
firelight_lighting-1.0.1.dist-info/RECORD
