Metadata-Version: 2.1
Name: firelight-lighting
Version: 1.0.1
Summary: Sync up colored lights to the contents of your screen.
Home-page: https://github.com/roshie548/firelight
Author: Roshan Kumaraswamy
Author-email: rkumaraswamy@berkeley.edu
License: UNKNOWN
Project-URL: Bug Tracker, https://github.com/roshie548/firelight/issues
Platform: UNKNOWN
Classifier: Programming Language :: Python :: 3
Classifier: License :: OSI Approved :: MIT License
Classifier: Operating System :: OS Independent
Requires-Python: >=3.6
License-File: LICENSE
Requires-Dist: numpy
Requires-Dist: scipy
Requires-Dist: mss
Requires-Dist: lifxlan
